factoryboi/__init__.py
factoryboi-0.0.1.dist-info/LICENSE.md
factoryboi-0.0.1.dist-info/METADATA
factoryboi-0.0.1.dist-info/WHEEL
factoryboi-0.0.1.dist-info/top_level.txt
factoryboi-0.0.1.dist-info/RECORD
