Metadata-Version: 2.1
Name: factoryboi
Version: 0.0.1
Summary: package that will tell you have a typo
Home-page: https://github.com/pypa/sampleproject
Author: Hubert Bryłkowski
Author-email: hubert@brylkowski.com
License: UNKNOWN
Platform: UNKNOWN
Classifier: Programming Language :: Python :: 3
Classifier: License :: OSI Approved :: MIT License
Classifier: Operating System :: OS Independent
